hydra_plugins/list_sweeper_plugin/__init__.py
hydra_plugins/list_sweeper_plugin/list_sweeper.py
hydra_plugins/list_sweeper_plugin/py.typed
hydra_list_sweeper-1.0.1.dist-info/METADATA
hydra_list_sweeper-1.0.1.dist-info/WHEEL
hydra_list_sweeper-1.0.1.dist-info/top_level.txt
hydra_list_sweeper-1.0.1.dist-info/RECORD
