Metadata-Version: 2.1
Name: hydra-list-sweeper
Version: 1.0.1
Summary: List Hydra Sweeper plugin
Home-page: https://github.com/facebookresearch/hydra/
Author: Philipp Dahlinger
Author-email: philipp.dahlinger@kit.edu
Classifier: License :: OSI Approved :: MIT License
Classifier: Programming Language :: Python :: 3.7
Classifier: Programming Language :: Python :: 3.8
Classifier: Programming Language :: Python :: 3.9
Classifier: Programming Language :: Python :: 3.10
Classifier: Programming Language :: Python :: 3.11
Classifier: Operating System :: OS Independent
Requires-Dist: hydra-core
